mysqlhelper/__init__.py
mysqlhelper/mysql_connection_pool.py
mysqlhelper/__pycache__/__init__.cpython-38.pyc
mysqlhelper/__pycache__/mysql_connection_pool.cpython-38.pyc
sc_mysqlhelper-0.1.4.dist-info/LICENSE
sc_mysqlhelper-0.1.4.dist-info/METADATA
sc_mysqlhelper-0.1.4.dist-info/WHEEL
sc_mysqlhelper-0.1.4.dist-info/top_level.txt
sc_mysqlhelper-0.1.4.dist-info/RECORD
