Metadata-Version: 1.2
Name: sc-mysqlhelper
Version: 0.1.4
Summary: A helper for MySQL using python language
Home-page: https://github.com/Scott-Lau/sc-mysqlhelper
Author: Scott Lau
Author-email: exceedego@126.com
License: MIT
Keywords: mysql helper connection pool python
Platform: POSIX
Classifier: Programming Language :: Python :: 3
Classifier: License :: OSI Approved :: MIT License
Classifier: Operating System :: OS Independent
Requires-Python: >=3.6
